pykesko-0.0.4.dist-info/METADATA
pykesko-0.0.4.dist-info/WHEEL
pykesko-0.0.4.dist-info/license_files/LICENSE
pykesko/backend/backend.py
pykesko/backend/bindings.py
pykesko/backend/tcp.py
pykesko/backend/__init__.py
pykesko/color.py
pykesko/config.py
pykesko/envs/spider.py
pykesko/envs/__init__.py
pykesko/kesko.py
pykesko/protocol/commands.py
pykesko/protocol/communicator.py
pykesko/protocol/request.py
pykesko/protocol/response.py
pykesko/protocol/__init__.py
pykesko/utils.py
pykesko/__init__.py
pykesko/pykesko.cp310-win_amd64.pyd
pykesko-0.0.4.dist-info/RECORD
