Metadata-Version: 2.1
Name: pykesko
Version: 0.0.4
Classifier: License :: OSI Approved :: MIT License
Classifier: Programming Language :: Python
Classifier: Programming Language :: Python :: 3
Classifier: Programming Language :: Python :: 3.7
Classifier: Programming Language :: Python :: 3.8
Classifier: Programming Language :: Python :: 3.9
Classifier: Programming Language :: Python :: 3.10
Classifier: Programming Language :: Python :: 3.11
Requires-Dist: numpy
Requires-Dist: requests
Requires-Dist: pydantic
Requires-Dist: gym
Requires-Dist: flake8; extra == 'dev'
Requires-Dist: pytest; extra == 'dev'
Requires-Dist: black; extra == 'dev'
Requires-Dist: twine; extra == 'dev'
Provides-Extra: dev
License-File: LICENSE
Summary: Robotics Simulator written in Rust
Keywords: Robotics,Machine learning,Reinforcement learning,Rust,Bevy
Author-email: Toni Axelsson <toniaxelsson@gmail.com>
Requires-Python: >=3.7
